nonebot_plugin_memos/__init__.py
nonebot_plugin_memos/cache.py
nonebot_plugin_memos/client.py
nonebot_plugin_memos/config.py
nonebot_plugin_memos/db.py
nonebot_plugin_memos/depend.py
nonebot_plugin_memos/model.py
nonebot_plugin_memos/util.py
nonebot_plugin_memos/migrations/af113b78e1a7_first_revision.py
nonebot_plugin_memos/migrations/cc54f4b17487_memo_record.py
nonebot_plugin_memos-0.1.0b15.dist-info/LICENSE
nonebot_plugin_memos-0.1.0b15.dist-info/METADATA
nonebot_plugin_memos-0.1.0b15.dist-info/WHEEL
nonebot_plugin_memos-0.1.0b15.dist-info/top_level.txt
nonebot_plugin_memos-0.1.0b15.dist-info/RECORD
