Metadata-Version: 2.2
Name: nonebot-plugin-memos
Version: 0.1.0b15
Summary: nonebot2 plugin for memos
Author-email: eya46 <admin@eya46.com>
License: The MIT License (MIT)
Requires-Python: >=3.10
License-File: LICENSE
Requires-Dist: filetype>=1.2.0
Requires-Dist: nonebot-plugin-alconna>=0.54.2
Requires-Dist: nonebot-plugin-orm>=0.7.6
Requires-Dist: nonebot-plugin-session>=0.3.2
Requires-Dist: nonebot-plugin-session-orm>=0.2.2
Requires-Dist: nonebot2[httpx]>=2.4.1
